plogs/__init__.py
plogs/colors.py
plogs/jsonlogger.py
plogs/plogs.py
plogs/test.py
plogs/logzero/__init__.py
plogs/logzero/colors.py
plogs/logzero/jsonlogger.py
plogs-2.0.dist-info/METADATA
plogs-2.0.dist-info/WHEEL
plogs-2.0.dist-info/top_level.txt
plogs-2.0.dist-info/RECORD
