Metadata-Version: 2.1
Name: plogs
Version: 2.0
Summary: pretty log
Home-page: https://github.com/liziqiang0523/clog.git
Author: liziqiang
Author-email: 739669518@qq.com
License: UNKNOWN
Keywords: pip,plogs
Platform: any
